rpithingamajigs/__init__.py
rpithingamajigs/chardisplay/__init__.py
rpithingamajigs/chardisplay/display.py
rpithingamajigs/chardisplay/display_i2c.py
rpithingamajigs/chardisplay_sysinfo/__init__.py
rpithingamajigs/chardisplay_sysinfo/chardisplay_sysinfo.py
rpithingamajigs/chardisplay_sysinfo/cli_chardisplay_sysinfo.py
rpithingamajigs/lcdd/__init__.py
rpithingamajigs/lcdd/client/__init__.py
rpithingamajigs/lcdd/client/cli_lcdd_client.py
rpithingamajigs/lcdd/client/ignorant_lcdd_client.py
rpithingamajigs/lcdd/client/lcdd_client.py
rpithingamajigs/lcdd/service/__init__.py
rpithingamajigs/lcdd/service/cli_lcdd_service.py
rpithingamajigs/lcdd/service/configuration.py
rpithingamajigs/lcdd/service/lcdd.py
rpithingamajigs/lcdd/service/lcdd_dbus_service.py
rpithingamajigs/logging/__init__.py
rpithingamajigs/logging/click_log_handler.py
rpithingamajigs/platform/__init__.py
rpithingamajigs/platform/detect_platform.py
rpithingamajigs/temperature_sensor/__init__.py
rpithingamajigs/temperature_sensor/dht22_reader.py
rpithingamajigs/temperature_sensor/temperature_sensor.py
rpi_thingamajigs-0.6.202302122050.dist-info/LICENSE
rpi_thingamajigs-0.6.202302122050.dist-info/METADATA
rpi_thingamajigs-0.6.202302122050.dist-info/WHEEL
rpi_thingamajigs-0.6.202302122050.dist-info/entry_points.txt
rpi_thingamajigs-0.6.202302122050.dist-info/top_level.txt
rpi_thingamajigs-0.6.202302122050.dist-info/RECORD
