Metadata-Version: 2.1
Name: rpi-thingamajigs
Version: 0.6.202302122050
Summary: Raspberry Pi Thingamajigs is a collection of Raspberry Pi related utilities like LCDD or character display interfaces.
Home-page: https://gitlab.com/mirkoboehm/rpi-thingamajigs
Author: Mirko Boehm
Author-email: mirko@kde.org
License: UNKNOWN
Platform: UNKNOWN
Classifier: Programming Language :: Python :: 3
Classifier: License :: OSI Approved :: Apache Software License
Classifier: Operating System :: OS Independent
Classifier: Development Status :: 4 - Beta
Requires-Python: >=3.6
License-File: LICENSE
Requires-Dist: Click
Requires-Dist: humanize
Requires-Dist: psutil
Requires-Dist: pydbus
Requires-Dist: pygi
Requires-Dist: pyyaml
